RussianLang/__init__.py
RussianLang-0.2.dist-info/METADATA
RussianLang-0.2.dist-info/WHEEL
RussianLang-0.2.dist-info/top_level.txt
RussianLang-0.2.dist-info/RECORD
