Metadata-Version: 2.1
Name: RussianLang
Version: 0.2
Summary: Библиотека для программирования на python русским языком
Home-page: https://github.com/Dron3916/RussianLanguage
Author: Rodionov Andrew
Author-email: dron3915work@gmail.com
License: UNKNOWN
Platform: UNKNOWN
Classifier: Programming Language :: Python :: 3
Classifier: License :: OSI Approved :: MIT License
Classifier: Operating System :: OS Independent
Requires-Python: >=3.9
